abstractforge/__init__.py
abstractforge-0.0.1.dist-info/licenses/LICENSE
abstractforge-0.0.1.dist-info/METADATA
abstractforge-0.0.1.dist-info/WHEEL
abstractforge-0.0.1.dist-info/top_level.txt
abstractforge-0.0.1.dist-info/RECORD
