Metadata-Version: 2.4
Name: AbstractForge
Version: 0.0.1
Summary: PLACEHOLDER PROJECT - Future extension of capabilities for AbstractLLM
Author-email: AbstractForge Team <contact@abstractforge.dev>
License-Expression: MIT
Project-URL: Homepage, https://github.com/abstractforge/abstractforge
Project-URL: Documentation, https://github.com/abstractforge/abstractforge
Project-URL: Repository, https://github.com/abstractforge/abstractforge
Project-URL: Bug Tracker, https://github.com/abstractforge/abstractforge/issues
Keywords: placeholder,abstractllm,extension,capabilities
Classifier: Development Status :: 1 - Planning
Classifier: Intended Audience :: Developers
Classifier: Programming Language :: Python :: 3
Classifier: Programming Language :: Python :: 3.8
Classifier: Programming Language :: Python :: 3.9
Classifier: Programming Language :: Python :: 3.10
Classifier: Programming Language :: Python :: 3.11
Classifier: Programming Language :: Python :: 3.12
Classifier: Topic :: Software Development :: Libraries :: Python Modules
Requires-Python: >=3.8
License-File: LICENSE
Provides-Extra: dev
Requires-Dist: build; extra == "dev"
Requires-Dist: twine; extra == "dev"
Dynamic: license-file
